autodocstrings/__init__.py
autodocstrings/main.py
autodocstrings-0.1.3.dist-info/LICENSE
autodocstrings-0.1.3.dist-info/METADATA
autodocstrings-0.1.3.dist-info/WHEEL
autodocstrings-0.1.3.dist-info/entry_points.txt
autodocstrings-0.1.3.dist-info/top_level.txt
autodocstrings-0.1.3.dist-info/RECORD
