Metadata-Version: 2.1
Name: autodocstrings
Version: 0.1.3
Summary: A tool for updating docstrings in Python files using the OpenAI API
Home-page: https://github.com/cdesarmeaux/autodocstrings
Author: Casimir Desarmeaux
Author-email: casimir.desarmeaux@gmail.com
Classifier: Programming Language :: Python :: 3.6
Classifier: License :: OSI Approved :: MIT License
Classifier: Operating System :: OS Independent
Requires-Python: >=3.6
License-File: LICENSE
Requires-Dist: astor
Requires-Dist: openai
Requires-Dist: typer
Requires-Dist: black
